{
  "manual": false,
  "urls": {
    "873425530": {
      "success": {
        "timestamp": "2025-04-02T03:46:53.733129511Z"
      },
      "error": {
        "timestamp": "2025-04-01T04:32:19.893695870Z",
        "code": -1
      }
    },
    "1768650598": {
      "success": {
        "timestamp": "2025-04-02T03:46:53.735797803Z"
      },
      "error": {
        "timestamp": "2025-04-01T04:32:24.895157272Z",
        "code": -1
      }
    },
    "1675899851": {
      "error": {
        "timestamp": "2026-05-29T06:09:45.870173573Z",
        "code": 200
      }
    },
    "396036173": {
      "error": {
        "timestamp": "2026-05-29T06:09:48.763406661Z",
        "code": 200
      }
    },
    "709989412": {
      "error": {
        "timestamp": "2026-05-29T06:09:52.175960895Z",
        "code": 200
      }
    },
    "-1546938631": {
      "error": {
        "timestamp": "2026-05-29T06:09:53.172842068Z",
        "code": 200
      }
    }
  }
}