{
  "manual": false,
  "urls": {
    "960171333": {
      "success": {
        "timestamp": "2025-11-01T04:47:22.535266300Z"
      },
      "error": {
        "timestamp": "2025-10-30T05:08:02.934852849Z",
        "code": 503
      }
    },
    "-623490175": {
      "success": {
        "timestamp": "2024-11-25T04:43:29.835346372Z"
      },
      "error": {
        "timestamp": "2024-11-22T04:32:41.597848505Z",
        "code": -1
      }
    },
    "744724431": {
      "success": {
        "timestamp": "2026-04-24T06:25:15.956926242Z"
      },
      "error": {
        "timestamp": "2026-04-23T05:51:35.757695479Z",
        "code": -1
      }
    }
  }
}