{
  "manual" : false,
  "urls" : {
    "1442394795" : {
      "success" : {
        "timestamp" : "2025-12-10T03:54:42.539565923Z"
      }
    },
    "-1819512061" : {
      "success" : {
        "timestamp" : "2025-12-10T03:54:44.021546254Z"
      }
    },
    "-1943466268" : {
      "success" : {
        "timestamp" : "2025-12-10T03:54:44.522727682Z"
      }
    },
    "-1031842258" : {
      "success" : {
        "timestamp" : "2025-12-10T03:54:45.023968993Z"
      }
    },
    "-935973395" : {
      "success" : {
        "timestamp" : "2025-12-10T03:54:45.450040200Z"
      }
    }
  }
}