{
  "manual": false,
  "urls": {
    "-1602665348": {
      "success": {
        "timestamp": "2026-05-19T04:34:15.524849941Z"
      },
      "error": {
        "timestamp": "2026-05-18T04:40:53.849989132Z",
        "code": 503
      }
    },
    "627144208": {
      "success": {
        "timestamp": "2026-05-19T04:34:15.230341375Z"
      },
      "error": {
        "timestamp": "2026-05-18T04:40:53.244351404Z",
        "code": 503
      }
    },
    "-381867040": {
      "success": {
        "timestamp": "2025-12-22T03:46:33.163559893Z"
      }
    },
    "-2104421844": {
      "success": {
        "timestamp": "2025-12-22T03:46:33.374200894Z"
      }
    },
    "2104062834": {
      "success": {
        "timestamp": "2026-05-23T04:29:43.426994158Z"
      }
    },
    "-70595883": {
      "success": {
        "timestamp": "2026-05-23T04:29:43.603513101Z"
      }
    }
  }
}