{
  "manual": false,
  "urls": {
    "406900210": {
      "success": {
        "timestamp": "2026-01-10T03:39:14.253689018Z"
      },
      "error": {
        "timestamp": "2026-01-09T03:40:52.696656022Z",
        "code": 503
      }
    },
    "123909699": {
      "success": {
        "timestamp": "2026-05-29T04:37:13.877534397Z"
      },
      "error": {
        "timestamp": "2026-05-28T04:35:38.996830778Z",
        "code": 503
      }
    },
    "1799591078": {
      "success": {
        "timestamp": "2026-01-05T03:47:12.494600083Z"
      },
      "error": {
        "timestamp": "2026-01-04T03:43:57.242841506Z",
        "code": 503
      }
    },
    "-832051750": {
      "success": {
        "timestamp": "2026-03-04T03:52:29.516136059Z"
      },
      "error": {
        "timestamp": "2026-03-03T03:56:09.214452633Z",
        "code": 503
      }
    }
  }
}