{
  "manual": false,
  "urls": {
    "-1451006604": {
      "success": {
        "timestamp": "2026-03-18T05:21:11.248597700Z"
      }
    },
    "-1929290984": {
      "success": {
        "timestamp": "2026-03-18T05:21:15.408949709Z"
      }
    },
    "177238168": {
      "success": {
        "timestamp": "2026-03-18T05:21:17.198735343Z"
      }
    },
    "-1986205580": {
      "success": {
        "timestamp": "2026-03-18T05:21:19.985107889Z"
      }
    },
    "1671267727": {
      "success": {
        "timestamp": "2026-03-18T05:21:25.222881285Z"
      }
    },
    "-492176021": {
      "success": {
        "timestamp": "2026-03-18T05:21:32.826369918Z"
      }
    }
  }
}