{
  "manual": false,
  "urls": {
    "77773367": {
      "success": {
        "timestamp": "2025-08-22T04:15:19.163019883Z"
      }
    },
    "515234571": {
      "success": {
        "timestamp": "2026-02-17T04:53:46.753149768Z"
      },
      "error": {
        "timestamp": "2026-02-16T05:07:04.377421150Z",
        "code": 502
      }
    },
    "1500020483": {
      "success": {
        "timestamp": "2026-02-17T04:53:46.675932422Z"
      },
      "error": {
        "timestamp": "2026-02-16T05:07:04.352693663Z",
        "code": 502
      }
    },
    "-51473827": {
      "success": {
        "timestamp": "2025-08-22T04:15:19.729300741Z"
      }
    },
    "-2118954139": {
      "success": {
        "timestamp": "2025-08-22T04:15:19.917871098Z"
      }
    },
    "-1989706945": {
      "success": {
        "timestamp": "2026-02-17T04:53:46.072566278Z"
      },
      "error": {
        "timestamp": "2026-02-16T05:07:04.177215377Z",
        "code": 502
      }
    }
  }
}