{
  "manual": false,
  "urls": {
    "1143855663": {
      "success": {
        "timestamp": "2026-05-20T05:43:16.285497102Z"
      },
      "error": {
        "timestamp": "2026-05-19T05:41:08.237561738Z",
        "code": 502
      }
    },
    "1385428733": {
      "success": {
        "timestamp": "2025-06-03T04:15:10.373398752Z"
      }
    },
    "-1212081511": {
      "success": {
        "timestamp": "2025-06-03T04:15:14.367701758Z"
      }
    },
    "2001589055": {
      "success": {
        "timestamp": "2026-03-28T04:53:14.055766092Z"
      }
    }
  }
}