{
  "manual": false,
  "urls": {
    "-1805052093": {
      "success": {
        "timestamp": "2024-03-03T03:49:52.205907291Z"
      },
      "error": {
        "timestamp": "2024-03-01T03:50:10.138629535Z",
        "code": 504
      }
    },
    "1475687295": {
      "success": {
        "timestamp": "2023-05-24T03:34:57.458001Z"
      }
    },
    "735568017": {
      "success": {
        "timestamp": "2026-03-25T05:28:47.537531544Z"
      },
      "error": {
        "timestamp": "2026-03-24T05:02:47.451740122Z",
        "code": -1
      }
    },
    "1748226212": {
      "success": {
        "timestamp": "2026-04-25T06:08:44.958438257Z"
      }
    }
  }
}