{
  "manual": false,
  "urls": {
    "416468874": {
      "success": {
        "timestamp": "2025-10-31T04:57:36.617069841Z"
      },
      "error": {
        "timestamp": "2025-10-30T05:07:31.184357934Z",
        "code": 503
      }
    },
    "-154983738": {
      "success": {
        "timestamp": "2025-10-31T04:57:37.640781861Z"
      },
      "error": {
        "timestamp": "2025-10-29T04:41:47.563484844Z",
        "code": 503
      }
    },
    "208572074": {
      "success": {
        "timestamp": "2025-10-31T04:57:37.130461776Z"
      },
      "error": {
        "timestamp": "2025-10-29T04:41:46.940173477Z",
        "code": 503
      }
    },
    "-1492400131": {
      "success": {
        "timestamp": "2026-04-25T06:13:36.954624551Z"
      }
    }
  }
}